{
    "imgHeight": 1024, 
    "imgWidth": 2048, 
    "objects": [
        {
            "label": "road", 
            "polygon": [
                [
                    974, 
                    473
                ], 
                [
                    919, 
                    471
                ], 
                [
                    898, 
                    479
                ], 
                [
                    864, 
                    476
                ], 
                [
                    759, 
                    478
                ], 
                [
                    13, 
                    692
                ], 
                [
                    18, 
                    945
                ], 
                [
                    1229, 
                    870
                ], 
                [
                    1944, 
                    910
                ], 
                [
                    1183, 
                    498
                ], 
                [
                    1156, 
                    489
                ]
            ]
        }, 
        {
            "label": "cargroup", 
            "polygon": [
                [
                    710, 
                    401
                ], 
                [
                    714, 
                    454
                ], 
                [
                    749, 
                    452
                ], 
                [
                    761, 
                    455
                ], 
                [
                    839, 
                    455
                ], 
                [
                    851, 
                    452
                ], 
                [
                    855, 
                    422
                ], 
                [
                    835, 
                    377
                ], 
                [
                    771, 
                    387
                ], 
                [
                    752, 
                    409
                ], 
                [
                    745, 
                    400
                ], 
                [
                    730, 
                    399
                ]
            ]
        }, 
        {
            "label": "bicycle", 
            "polygon": [
                [
                    615, 
                    431
                ], 
                [
                    598, 
                    436
                ], 
                [
                    594, 
                    439
                ], 
                [
                    591, 
                    446
                ], 
                [
                    589, 
                    471
                ], 
                [
                    594, 
                    477
                ], 
                [
                    609, 
                    482
                ], 
                [
                    616, 
                    469
                ], 
                [
                    620, 
                    461
                ], 
                [
                    621, 
                    447
                ]
            ]
        }, 
        {
            "label": "person", 
            "polygon": [
                [
                    626, 
                    378
                ], 
                [
                    622, 
                    378
                ], 
                [
                    620, 
                    380
                ], 
                [
                    619, 
                    386
                ], 
                [
                    618, 
                    390
                ], 
                [
                    611, 
                    398
                ], 
                [
                    610, 
                    402
                ], 
                [
                    614, 
                    403
                ], 
                [
                    620, 
                    403
                ], 
                [
                    628, 
                    404
                ], 
                [
                    635, 
                    405
                ], 
                [
                    636, 
                    401
                ], 
                [
                    635, 
                    394
                ], 
                [
                    633, 
                    392
                ], 
                [
                    626, 
                    390
                ], 
                [
                    625, 
                    389
                ], 
                [
                    627, 
                    380
                ]
            ]
        }, 
        {
            "label": "bicycle", 
            "polygon": [
                [
                    264, 
                    431
                ], 
                [
                    256, 
                    447
                ], 
                [
                    255, 
                    452
                ], 
                [
                    255, 
                    489
                ], 
                [
                    256, 
                    494
                ], 
                [
                    258, 
                    495
                ], 
                [
                    265, 
                    494
                ], 
                [
                    271, 
                    480
                ], 
                [
                    270, 
                    461
                ], 
                [
                    273, 
                    456
                ], 
                [
                    277, 
                    454
                ], 
                [
                    279, 
                    455
                ], 
                [
                    283, 
                    460
                ], 
                [
                    292, 
                    484
                ], 
                [
                    298, 
                    494
                ], 
                [
                    302, 
                    493
                ], 
                [
                    308, 
                    484
                ], 
                [
                    310, 
                    459
                ], 
                [
                    300, 
                    437
                ], 
                [
                    290, 
                    433
                ]
            ]
        }, 
        {
            "label": "person", 
            "polygon": [
                [
                    320, 
                    302
                ], 
                [
                    310, 
                    311
                ], 
                [
                    312, 
                    325
                ], 
                [
                    270, 
                    356
                ], 
                [
                    279, 
                    356
                ], 
                [
                    302, 
                    344
                ], 
                [
                    307, 
                    344
                ], 
                [
                    312, 
                    348
                ], 
                [
                    315, 
                    359
                ], 
                [
                    315, 
                    376
                ], 
                [
                    312, 
                    392
                ], 
                [
                    323, 
                    464
                ], 
                [
                    329, 
                    484
                ], 
                [
                    333, 
                    484
                ], 
                [
                    337, 
                    475
                ], 
                [
                    335, 
                    434
                ], 
                [
                    339, 
                    423
                ], 
                [
                    347, 
                    367
                ], 
                [
                    352, 
                    360
                ], 
                [
                    342, 
                    332
                ], 
                [
                    332, 
                    326
                ], 
                [
                    327, 
                    315
                ], 
                [
                    326, 
                    305
                ], 
                [
                    324, 
                    303
                ]
            ]
        }, 
        {
            "label": "person", 
            "polygon": [
                [
                    173, 
                    336
                ], 
                [
                    168, 
                    337
                ], 
                [
                    165, 
                    339
                ], 
                [
                    164, 
                    343
                ], 
                [
                    161, 
                    357
                ], 
                [
                    158, 
                    365
                ], 
                [
                    158, 
                    369
                ], 
                [
                    167, 
                    374
                ], 
                [
                    170, 
                    381
                ], 
                [
                    171, 
                    388
                ], 
                [
                    182, 
                    469
                ], 
                [
                    182, 
                    476
                ], 
                [
                    185, 
                    474
                ], 
                [
                    190, 
                    450
                ], 
                [
                    193, 
                    440
                ], 
                [
                    193, 
                    393
                ], 
                [
                    209, 
                    393
                ], 
                [
                    210, 
                    386
                ], 
                [
                    197, 
                    365
                ], 
                [
                    182, 
                    349
                ], 
                [
                    182, 
                    346
                ]
            ]
        }, 
        {
            "label": "pole", 
            "polygon": [
                [
                    137, 
                    587
                ], 
                [
                    130, 
                    587
                ], 
                [
                    108, 
                    49
                ], 
                [
                    113, 
                    51
                ], 
                [
                    137, 
                    588
                ]
            ]
        }, 
        {
            "label": "bicycle", 
            "polygon": [
                [
                    51, 
                    454
                ], 
                [
                    34, 
                    454
                ], 
                [
                    10, 
                    477
                ], 
                [
                    10, 
                    519
                ], 
                [
                    18, 
                    538
                ], 
                [
                    26, 
                    543
                ], 
                [
                    39, 
                    547
                ], 
                [
                    60, 
                    547
                ], 
                [
                    72, 
                    544
                ], 
                [
                    81, 
                    535
                ], 
                [
                    84, 
                    520
                ], 
                [
                    73, 
                    512
                ], 
                [
                    58, 
                    511
                ], 
                [
                    47, 
                    496
                ]
            ]
        }, 
        {
            "label": "pole", 
            "polygon": [
                [
                    504, 
                    403
                ], 
                [
                    509, 
                    412
                ], 
                [
                    510, 
                    480
                ], 
                [
                    491, 
                    481
                ], 
                [
                    489, 
                    414
                ], 
                [
                    497, 
                    401
                ], 
                [
                    497, 
                    330
                ], 
                [
                    500, 
                    332
                ]
            ]
        }, 
        {
            "label": "sidewalk", 
            "polygon": [
                [
                    162, 
                    545
                ], 
                [
                    146, 
                    611
                ], 
                [
                    411, 
                    540
                ], 
                [
                    593, 
                    497
                ], 
                [
                    588, 
                    491
                ], 
                [
                    563, 
                    497
                ], 
                [
                    546, 
                    496
                ], 
                [
                    518, 
                    492
                ], 
                [
                    489, 
                    500
                ], 
                [
                    479, 
                    496
                ], 
                [
                    471, 
                    490
                ], 
                [
                    447, 
                    487
                ], 
                [
                    437, 
                    518
                ], 
                [
                    431, 
                    522
                ], 
                [
                    417, 
                    524
                ], 
                [
                    199, 
                    522
                ], 
                [
                    201, 
                    561
                ], 
                [
                    199, 
                    567
                ], 
                [
                    196, 
                    572
                ], 
                [
                    192, 
                    574
                ], 
                [
                    187, 
                    573
                ], 
                [
                    183, 
                    570
                ], 
                [
                    179, 
                    562
                ], 
                [
                    175, 
                    532
                ]
            ]
        }, 
        {
            "label": "vegetation", 
            "polygon": [
                [
                    401, 
                    82
                ], 
                [
                    320, 
                    58
                ], 
                [
                    296, 
                    56
                ], 
                [
                    277, 
                    66
                ], 
                [
                    273, 
                    108
                ], 
                [
                    287, 
                    131
                ], 
                [
                    313, 
                    160
                ], 
                [
                    395, 
                    185
                ], 
                [
                    409, 
                    184
                ], 
                [
                    417, 
                    180
                ], 
                [
                    424, 
                    169
                ], 
                [
                    412, 
                    86
                ]
            ]
        }, 
        {
            "label": "vegetation", 
            "polygon": [
                [
                    708, 
                    61
                ], 
                [
                    713, 
                    38
                ], 
                [
                    616, 
                    39
                ], 
                [
                    530, 
                    89
                ], 
                [
                    528, 
                    110
                ], 
                [
                    533, 
                    131
                ], 
                [
                    599, 
                    217
                ], 
                [
                    644, 
                    232
                ], 
                [
                    661, 
                    244
                ], 
                [
                    707, 
                    299
                ], 
                [
                    728, 
                    333
                ], 
                [
                    751, 
                    342
                ], 
                [
                    865, 
                    364
                ], 
                [
                    913, 
                    382
                ], 
                [
                    931, 
                    383
                ], 
                [
                    942, 
                    372
                ], 
                [
                    948, 
                    344
                ], 
                [
                    891, 
                    330
                ], 
                [
                    844, 
                    312
                ], 
                [
                    831, 
                    303
                ], 
                [
                    802, 
                    251
                ], 
                [
                    735, 
                    231
                ], 
                [
                    739, 
                    208
                ], 
                [
                    786, 
                    194
                ], 
                [
                    798, 
                    182
                ], 
                [
                    763, 
                    135
                ], 
                [
                    730, 
                    100
                ]
            ]
        }, 
        {
            "label": "building", 
            "polygon": [
                [
                    278, 
                    5
                ], 
                [
                    169, 
                    14
                ], 
                [
                    168, 
                    186
                ], 
                [
                    201, 
                    319
                ], 
                [
                    220, 
                    321
                ], 
                [
                    249, 
                    320
                ], 
                [
                    269, 
                    314
                ], 
                [
                    288, 
                    300
                ], 
                [
                    295, 
                    213
                ], 
                [
                    284, 
                    197
                ], 
                [
                    246, 
                    166
                ], 
                [
                    241, 
                    155
                ], 
                [
                    236, 
                    131
                ], 
                [
                    240, 
                    51
                ], 
                [
                    263, 
                    48
                ], 
                [
                    310, 
                    32
                ], 
                [
                    342, 
                    31
                ], 
                [
                    375, 
                    40
                ], 
                [
                    440, 
                    78
                ], 
                [
                    442, 
                    86
                ], 
                [
                    469, 
                    89
                ], 
                [
                    479, 
                    65
                ], 
                [
                    504, 
                    42
                ], 
                [
                    518, 
                    12
                ]
            ]
        }, 
        {
            "label": "sky", 
            "polygon": [
                [
                    1133, 
                    10
                ], 
                [
                    753, 
                    15
                ], 
                [
                    735, 
                    40
                ], 
                [
                    733, 
                    54
                ], 
                [
                    736, 
                    61
                ], 
                [
                    740, 
                    65
                ], 
                [
                    764, 
                    68
                ], 
                [
                    777, 
                    72
                ], 
                [
                    786, 
                    81
                ], 
                [
                    791, 
                    90
                ], 
                [
                    790, 
                    115
                ], 
                [
                    798, 
                    125
                ], 
                [
                    816, 
                    126
                ], 
                [
                    836, 
                    133
                ], 
                [
                    848, 
                    141
                ], 
                [
                    850, 
                    164
                ], 
                [
                    843, 
                    207
                ], 
                [
                    843, 
                    221
                ], 
                [
                    873, 
                    234
                ], 
                [
                    910, 
                    241
                ], 
                [
                    916, 
                    221
                ], 
                [
                    936, 
                    198
                ], 
                [
                    965, 
                    178
                ], 
                [
                    1004, 
                    166
                ], 
                [
                    1019, 
                    155
                ], 
                [
                    1025, 
                    94
                ], 
                [
                    1040, 
                    63
                ], 
                [
                    1047, 
                    39
                ], 
                [
                    1068, 
                    30
                ], 
                [
                    1083, 
                    31
                ], 
                [
                    1098, 
                    38
                ], 
                [
                    1125, 
                    40
                ], 
                [
                    1130, 
                    35
                ]
            ]
        }, 
        {
            "label": "vegetation", 
            "polygon": [
                [
                    1018, 
                    198
                ], 
                [
                    993, 
                    204
                ], 
                [
                    975, 
                    212
                ], 
                [
                    963, 
                    223
                ], 
                [
                    955, 
                    241
                ], 
                [
                    951, 
                    281
                ], 
                [
                    960, 
                    295
                ], 
                [
                    1000, 
                    314
                ], 
                [
                    993, 
                    269
                ], 
                [
                    1000, 
                    263
                ], 
                [
                    1025, 
                    260
                ], 
                [
                    1031, 
                    275
                ], 
                [
                    1034, 
                    303
                ], 
                [
                    1023, 
                    348
                ], 
                [
                    1024, 
                    353
                ], 
                [
                    1030, 
                    359
                ], 
                [
                    1040, 
                    360
                ], 
                [
                    1045, 
                    359
                ], 
                [
                    1061, 
                    340
                ], 
                [
                    1072, 
                    292
                ], 
                [
                    1038, 
                    245
                ], 
                [
                    1041, 
                    240
                ], 
                [
                    1153, 
                    247
                ], 
                [
                    1203, 
                    200
                ], 
                [
                    1213, 
                    174
                ], 
                [
                    1189, 
                    75
                ], 
                [
                    1082, 
                    101
                ], 
                [
                    1046, 
                    148
                ], 
                [
                    1038, 
                    166
                ], 
                [
                    1038, 
                    179
                ], 
                [
                    1034, 
                    186
                ]
            ]
        }, 
        {
            "label": "vegetation", 
            "polygon": [
                [
                    1229, 
                    267
                ], 
                [
                    1177, 
                    274
                ], 
                [
                    1173, 
                    282
                ], 
                [
                    1179, 
                    297
                ], 
                [
                    1207, 
                    318
                ], 
                [
                    1216, 
                    318
                ], 
                [
                    1218, 
                    316
                ], 
                [
                    1225, 
                    273
                ]
            ]
        }, 
        {
            "label": "traffic sign", 
            "polygon": [
                [
                    1110, 
                    324
                ], 
                [
                    1109, 
                    323
                ], 
                [
                    1096, 
                    323
                ], 
                [
                    1099, 
                    346
                ], 
                [
                    1112, 
                    346
                ]
            ]
        }, 
        {
            "label": "traffic sign", 
            "polygon": [
                [
                    1186, 
                    321
                ], 
                [
                    1174, 
                    321
                ], 
                [
                    1174, 
                    347
                ], 
                [
                    1186, 
                    347
                ]
            ]
        }, 
        {
            "label": "traffic sign", 
            "polygon": [
                [
                    1276, 
                    232
                ], 
                [
                    1273, 
                    253
                ], 
                [
                    1274, 
                    254
                ], 
                [
                    1370, 
                    260
                ], 
                [
                    1384, 
                    248
                ], 
                [
                    1373, 
                    234
                ]
            ]
        }, 
        {
            "label": "pole", 
            "polygon": [
                [
                    1330, 
                    264
                ], 
                [
                    1328, 
                    264
                ], 
                [
                    1324, 
                    466
                ], 
                [
                    1325, 
                    465
                ]
            ]
        }, 
        {
            "label": "pole", 
            "polygon": [
                [
                    1242, 
                    458
                ], 
                [
                    1234, 
                    458
                ], 
                [
                    1235, 
                    399
                ], 
                [
                    1234, 
                    382
                ], 
                [
                    1233, 
                    262
                ], 
                [
                    1235, 
                    263
                ], 
                [
                    1239, 
                    400
                ], 
                [
                    1238, 
                    414
                ]
            ]
        }, 
        {
            "label": "person", 
            "polygon": [
                [
                    1254, 
                    369
                ], 
                [
                    1253, 
                    369
                ], 
                [
                    1247, 
                    371
                ], 
                [
                    1246, 
                    373
                ], 
                [
                    1246, 
                    379
                ], 
                [
                    1245, 
                    386
                ], 
                [
                    1245, 
                    424
                ], 
                [
                    1250, 
                    424
                ], 
                [
                    1250, 
                    424
                ], 
                [
                    1252, 
                    452
                ], 
                [
                    1251, 
                    453
                ], 
                [
                    1253, 
                    454
                ], 
                [
                    1254, 
                    454
                ], 
                [
                    1255, 
                    435
                ], 
                [
                    1258, 
                    428
                ], 
                [
                    1260, 
                    424
                ], 
                [
                    1261, 
                    396
                ], 
                [
                    1263, 
                    392
                ], 
                [
                    1259, 
                    387
                ], 
                [
                    1256, 
                    383
                ]
            ]
        }, 
        {
            "label": "person", 
            "polygon": [
                [
                    1287, 
                    365
                ], 
                [
                    1284, 
                    366
                ], 
                [
                    1282, 
                    368
                ], 
                [
                    1282, 
                    371
                ], 
                [
                    1283, 
                    376
                ], 
                [
                    1282, 
                    378
                ], 
                [
                    1279, 
                    381
                ], 
                [
                    1277, 
                    385
                ], 
                [
                    1277, 
                    389
                ], 
                [
                    1281, 
                    415
                ], 
                [
                    1279, 
                    457
                ], 
                [
                    1281, 
                    457
                ], 
                [
                    1282, 
                    456
                ], 
                [
                    1285, 
                    427
                ], 
                [
                    1287, 
                    425
                ], 
                [
                    1289, 
                    424
                ], 
                [
                    1290, 
                    424
                ], 
                [
                    1292, 
                    427
                ], 
                [
                    1295, 
                    458
                ], 
                [
                    1297, 
                    457
                ], 
                [
                    1297, 
                    433
                ], 
                [
                    1298, 
                    433
                ], 
                [
                    1298, 
                    408
                ], 
                [
                    1299, 
                    404
                ], 
                [
                    1300, 
                    381
                ], 
                [
                    1290, 
                    375
                ], 
                [
                    1288, 
                    372
                ]
            ]
        }, 
        {
            "label": "vegetation", 
            "polygon": [
                [
                    1593, 
                    27
                ], 
                [
                    1561, 
                    23
                ], 
                [
                    1397, 
                    24
                ], 
                [
                    1385, 
                    30
                ], 
                [
                    1374, 
                    40
                ], 
                [
                    1368, 
                    50
                ], 
                [
                    1363, 
                    135
                ], 
                [
                    1376, 
                    159
                ], 
                [
                    1415, 
                    186
                ], 
                [
                    1435, 
                    194
                ], 
                [
                    1473, 
                    203
                ], 
                [
                    1493, 
                    197
                ], 
                [
                    1498, 
                    184
                ], 
                [
                    1492, 
                    176
                ], 
                [
                    1476, 
                    165
                ], 
                [
                    1479, 
                    146
                ], 
                [
                    1501, 
                    120
                ], 
                [
                    1520, 
                    110
                ], 
                [
                    1547, 
                    87
                ], 
                [
                    1587, 
                    111
                ], 
                [
                    1672, 
                    141
                ], 
                [
                    1688, 
                    144
                ], 
                [
                    1712, 
                    144
                ], 
                [
                    1777, 
                    133
                ], 
                [
                    1793, 
                    127
                ], 
                [
                    1903, 
                    36
                ], 
                [
                    1894, 
                    29
                ]
            ]
        }, 
        {
            "label": "traffic sign", 
            "polygon": [
                [
                    1541, 
                    112
                ], 
                [
                    1501, 
                    146
                ], 
                [
                    1538, 
                    190
                ], 
                [
                    1566, 
                    156
                ], 
                [
                    1566, 
                    153
                ], 
                [
                    1556, 
                    147
                ], 
                [
                    1550, 
                    153
                ], 
                [
                    1546, 
                    154
                ], 
                [
                    1536, 
                    153
                ], 
                [
                    1531, 
                    151
                ], 
                [
                    1529, 
                    150
                ], 
                [
                    1528, 
                    145
                ], 
                [
                    1529, 
                    143
                ], 
                [
                    1533, 
                    140
                ], 
                [
                    1537, 
                    138
                ], 
                [
                    1550, 
                    136
                ], 
                [
                    1559, 
                    128
                ], 
                [
                    1559, 
                    126
                ]
            ]
        }, 
        {
            "label": "pole", 
            "polygon": [
                [
                    1549, 
                    525
                ], 
                [
                    1521, 
                    523
                ], 
                [
                    1526, 
                    386
                ], 
                [
                    1529, 
                    384
                ], 
                [
                    1533, 
                    373
                ], 
                [
                    1532, 
                    359
                ], 
                [
                    1534, 
                    201
                ], 
                [
                    1542, 
                    205
                ], 
                [
                    1544, 
                    371
                ], 
                [
                    1550, 
                    402
                ]
            ]
        }, 
        {
            "label": "fence", 
            "polygon": [
                [
                    1348, 
                    421
                ], 
                [
                    1340, 
                    512
                ], 
                [
                    1468, 
                    557
                ], 
                [
                    1468, 
                    437
                ]
            ]
        }, 
        {
            "label": "building", 
            "polygon": [
                [
                    2009, 
                    41
                ], 
                [
                    1989, 
                    40
                ], 
                [
                    1959, 
                    46
                ], 
                [
                    1944, 
                    58
                ], 
                [
                    1884, 
                    122
                ], 
                [
                    1822, 
                    168
                ], 
                [
                    1804, 
                    176
                ], 
                [
                    1748, 
                    190
                ], 
                [
                    1766, 
                    244
                ], 
                [
                    1764, 
                    299
                ], 
                [
                    1795, 
                    444
                ], 
                [
                    1802, 
                    454
                ], 
                [
                    1831, 
                    463
                ], 
                [
                    1941, 
                    482
                ], 
                [
                    2009, 
                    484
                ], 
                [
                    2014, 
                    475
                ], 
                [
                    2017, 
                    467
                ], 
                [
                    2038, 
                    40
                ]
            ]
        }, 
        {
            "label": "sidewalk", 
            "polygon": [
                [
                    1533, 
                    562
                ], 
                [
                    1524, 
                    580
                ], 
                [
                    1493, 
                    620
                ], 
                [
                    2029, 
                    916
                ], 
                [
                    2020, 
                    572
                ], 
                [
                    1766, 
                    512
                ], 
                [
                    1804, 
                    612
                ], 
                [
                    1798, 
                    620
                ], 
                [
                    1791, 
                    622
                ], 
                [
                    1744, 
                    629
                ], 
                [
                    1654, 
                    622
                ], 
                [
                    1584, 
                    606
                ], 
                [
                    1579, 
                    594
                ], 
                [
                    1601, 
                    562
                ], 
                [
                    1617, 
                    488
                ], 
                [
                    1580, 
                    495
                ], 
                [
                    1576, 
                    499
                ], 
                [
                    1572, 
                    544
                ], 
                [
                    1566, 
                    549
                ]
            ]
        }, 
        {
            "label": "pole", 
            "polygon": [
                [
                    1577, 
                    475
                ], 
                [
                    1571, 
                    474
                ], 
                [
                    1581, 
                    398
                ], 
                [
                    1582, 
                    399
                ], 
                [
                    1582, 
                    400
                ]
            ]
        }, 
        {
            "label": "pole", 
            "polygon": [
                [
                    1627, 
                    454
                ], 
                [
                    1624, 
                    454
                ], 
                [
                    1623, 
                    453
                ], 
                [
                    1624, 
                    395
                ], 
                [
                    1626, 
                    396
                ]
            ]
        }, 
        {
            "label": "building", 
            "polygon": [
                [
                    1315, 
                    22
                ], 
                [
                    1294, 
                    31
                ], 
                [
                    1270, 
                    17
                ], 
                [
                    1250, 
                    13
                ], 
                [
                    1190, 
                    15
                ], 
                [
                    1168, 
                    23
                ], 
                [
                    1160, 
                    30
                ], 
                [
                    1157, 
                    38
                ], 
                [
                    1167, 
                    45
                ], 
                [
                    1188, 
                    51
                ], 
                [
                    1201, 
                    59
                ], 
                [
                    1213, 
                    77
                ], 
                [
                    1223, 
                    98
                ], 
                [
                    1235, 
                    101
                ], 
                [
                    1248, 
                    95
                ], 
                [
                    1246, 
                    97
                ], 
                [
                    1292, 
                    89
                ], 
                [
                    1309, 
                    82
                ], 
                [
                    1323, 
                    57
                ]
            ]
        }, 
        {
            "label": "building", 
            "polygon": [
                [
                    420, 
                    450
                ], 
                [
                    479, 
                    450
                ], 
                [
                    482, 
                    197
                ], 
                [
                    455, 
                    183
                ], 
                [
                    439, 
                    195
                ], 
                [
                    425, 
                    211
                ], 
                [
                    427, 
                    209
                ], 
                [
                    406, 
                    241
                ], 
                [
                    398, 
                    256
                ], 
                [
                    394, 
                    269
                ], 
                [
                    397, 
                    280
                ], 
                [
                    404, 
                    285
                ], 
                [
                    422, 
                    293
                ], 
                [
                    427, 
                    306
                ]
            ]
        }, 
        {
            "label": "building", 
            "polygon": [
                [
                    9, 
                    349
                ], 
                [
                    88, 
                    343
                ], 
                [
                    93, 
                    32
                ], 
                [
                    18, 
                    31
                ]
            ]
        }, 
        {
            "label": "sky", 
            "polygon": [
                [
                    857, 
                    284
                ], 
                [
                    857, 
                    283
                ], 
                [
                    904, 
                    282
                ], 
                [
                    905, 
                    284
                ], 
                [
                    906, 
                    290
                ], 
                [
                    906, 
                    297
                ], 
                [
                    906, 
                    301
                ], 
                [
                    904, 
                    305
                ], 
                [
                    902, 
                    307
                ], 
                [
                    899, 
                    308
                ], 
                [
                    895, 
                    309
                ], 
                [
                    880, 
                    309
                ], 
                [
                    875, 
                    311
                ], 
                [
                    872, 
                    316
                ], 
                [
                    870, 
                    318
                ], 
                [
                    868, 
                    315
                ], 
                [
                    868, 
                    307
                ], 
                [
                    867, 
                    305
                ], 
                [
                    865, 
                    301
                ], 
                [
                    859, 
                    295
                ], 
                [
                    858, 
                    293
                ], 
                [
                    856, 
                    292
                ], 
                [
                    854, 
                    288
                ], 
                [
                    854, 
                    287
                ]
            ]
        }, 
        {
            "label": "vegetation", 
            "polygon": [
                [
                    1616, 
                    376
                ], 
                [
                    1611, 
                    429
                ], 
                [
                    1609, 
                    434
                ], 
                [
                    1596, 
                    427
                ], 
                [
                    1588, 
                    416
                ], 
                [
                    1587, 
                    412
                ], 
                [
                    1588, 
                    400
                ], 
                [
                    1587, 
                    395
                ], 
                [
                    1581, 
                    383
                ], 
                [
                    1581, 
                    380
                ], 
                [
                    1582, 
                    378
                ], 
                [
                    1589, 
                    383
                ], 
                [
                    1595, 
                    383
                ]
            ]
        }, 
        {
            "label": "ego vehicle", 
            "polygon": [
                [
                    0, 
                    956
                ], 
                [
                    197, 
                    928
                ], 
                [
                    461, 
                    901
                ], 
                [
                    737, 
                    879
                ], 
                [
                    1002, 
                    861
                ], 
                [
                    1135, 
                    857
                ], 
                [
                    1134, 
                    854
                ], 
                [
                    1109, 
                    844
                ], 
                [
                    1096, 
                    820
                ], 
                [
                    1098, 
                    783
                ], 
                [
                    1124, 
                    759
                ], 
                [
                    1151, 
                    755
                ], 
                [
                    1179, 
                    760
                ], 
                [
                    1202, 
                    777
                ], 
                [
                    1207, 
                    806
                ], 
                [
                    1199, 
                    832
                ], 
                [
                    1189, 
                    844
                ], 
                [
                    1169, 
                    854
                ], 
                [
                    1161, 
                    856
                ], 
                [
                    1429, 
                    871
                ], 
                [
                    1724, 
                    900
                ], 
                [
                    2047, 
                    927
                ], 
                [
                    2047, 
                    1023
                ], 
                [
                    0, 
                    1023
                ]
            ]
        }, 
        {
            "label": "rectification border", 
            "polygon": [
                [
                    416, 
                    0
                ], 
                [
                    967, 
                    12
                ], 
                [
                    2047, 
                    25
                ], 
                [
                    2047, 
                    0
                ]
            ]
        }, 
        {
            "label": "rectification border", 
            "polygon": [
                [
                    2047, 
                    509
                ], 
                [
                    2047, 
                    1023
                ], 
                [
                    2037, 
                    1023
                ]
            ]
        }, 
        {
            "label": "rectification border", 
            "polygon": [
                [
                    0, 
                    0
                ], 
                [
                    0, 
                    501
                ], 
                [
                    10, 
                    434
                ], 
                [
                    19, 
                    0
                ]
            ]
        }, 
        {
            "label": "rectification border", 
            "polygon": [
                [
                    1087, 
                    981
                ], 
                [
                    0, 
                    963
                ], 
                [
                    0, 
                    1023
                ], 
                [
                    1937, 
                    1023
                ]
            ]
        }, 
        {
            "label": "out of roi", 
            "polygon": [
                [
                    0, 
                    0
                ], 
                [
                    2048, 
                    0
                ], 
                [
                    2048, 
                    1024
                ], 
                [
                    0, 
                    1024
                ], 
                [
                    0, 
                    0
                ], 
                [
                    5, 
                    5
                ], 
                [
                    5, 
                    1019
                ], 
                [
                    2043, 
                    1019
                ], 
                [
                    2043, 
                    5
                ], 
                [
                    5, 
                    5
                ]
            ]
        }
    ]
}