{
    "imgHeight": 1024, 
    "imgWidth": 2048, 
    "objects": [
        {
            "label": "road", 
            "polygon": [
                [
                    33, 
                    997
                ], 
                [
                    2038, 
                    1010
                ], 
                [
                    1338, 
                    560
                ], 
                [
                    1344, 
                    597
                ], 
                [
                    1343, 
                    619
                ], 
                [
                    1158, 
                    617
                ], 
                [
                    1133, 
                    465
                ], 
                [
                    1123, 
                    441
                ], 
                [
                    1012, 
                    433
                ], 
                [
                    827, 
                    410
                ], 
                [
                    542, 
                    516
                ], 
                [
                    18, 
                    685
                ]
            ]
        }, 
        {
            "label": "sidewalk", 
            "polygon": [
                [
                    13, 
                    542
                ], 
                [
                    10, 
                    648
                ], 
                [
                    741, 
                    431
                ], 
                [
                    702, 
                    417
                ], 
                [
                    626, 
                    435
                ], 
                [
                    617, 
                    440
                ], 
                [
                    615, 
                    452
                ], 
                [
                    573, 
                    449
                ], 
                [
                    481, 
                    475
                ], 
                [
                    322, 
                    510
                ]
            ]
        }, 
        {
            "label": "vegetation", 
            "polygon": [
                [
                    14, 
                    12
                ], 
                [
                    18, 
                    136
                ], 
                [
                    13, 
                    146
                ], 
                [
                    5, 
                    302
                ], 
                [
                    5, 
                    307
                ], 
                [
                    9, 
                    313
                ], 
                [
                    28, 
                    319
                ], 
                [
                    103, 
                    331
                ], 
                [
                    117, 
                    331
                ], 
                [
                    122, 
                    333
                ], 
                [
                    148, 
                    331
                ], 
                [
                    150, 
                    330
                ], 
                [
                    150, 
                    326
                ], 
                [
                    142, 
                    283
                ], 
                [
                    142, 
                    241
                ], 
                [
                    146, 
                    221
                ], 
                [
                    155, 
                    211
                ], 
                [
                    175, 
                    205
                ], 
                [
                    200, 
                    202
                ], 
                [
                    232, 
                    201
                ], 
                [
                    256, 
                    198
                ], 
                [
                    326, 
                    179
                ], 
                [
                    369, 
                    175
                ], 
                [
                    366, 
                    158
                ], 
                [
                    345, 
                    134
                ], 
                [
                    337, 
                    118
                ], 
                [
                    319, 
                    106
                ], 
                [
                    261, 
                    81
                ], 
                [
                    245, 
                    60
                ], 
                [
                    222, 
                    60
                ], 
                [
                    191, 
                    67
                ], 
                [
                    182, 
                    75
                ], 
                [
                    175, 
                    90
                ], 
                [
                    167, 
                    93
                ], 
                [
                    158, 
                    94
                ], 
                [
                    114, 
                    81
                ], 
                [
                    89, 
                    65
                ], 
                [
                    83, 
                    57
                ], 
                [
                    77, 
                    42
                ], 
                [
                    30, 
                    20
                ], 
                [
                    29, 
                    17
                ]
            ]
        }, 
        {
            "label": "building", 
            "polygon": [
                [
                    232, 
                    7
                ], 
                [
                    603, 
                    7
                ], 
                [
                    681, 
                    0
                ], 
                [
                    735, 
                    8
                ], 
                [
                    743, 
                    28
                ], 
                [
                    727, 
                    84
                ], 
                [
                    722, 
                    88
                ], 
                [
                    711, 
                    108
                ], 
                [
                    705, 
                    137
                ], 
                [
                    714, 
                    178
                ], 
                [
                    727, 
                    213
                ], 
                [
                    727, 
                    228
                ], 
                [
                    714, 
                    250
                ], 
                [
                    714, 
                    248
                ], 
                [
                    700, 
                    241
                ], 
                [
                    646, 
                    223
                ], 
                [
                    645, 
                    220
                ], 
                [
                    627, 
                    200
                ], 
                [
                    594, 
                    186
                ], 
                [
                    588, 
                    229
                ], 
                [
                    582, 
                    351
                ], 
                [
                    584, 
                    411
                ], 
                [
                    581, 
                    418
                ], 
                [
                    573, 
                    423
                ], 
                [
                    462, 
                    450
                ], 
                [
                    241, 
                    491
                ], 
                [
                    220, 
                    231
                ], 
                [
                    431, 
                    262
                ], 
                [
                    429, 
                    147
                ], 
                [
                    395, 
                    63
                ], 
                [
                    322, 
                    65
                ], 
                [
                    292, 
                    42
                ], 
                [
                    249, 
                    31
                ], 
                [
                    242, 
                    27
                ], 
                [
                    223, 
                    15
                ]
            ]
        }, 
        {
            "label": "building", 
            "polygon": [
                [
                    742, 
                    2
                ], 
                [
                    1011, 
                    4
                ], 
                [
                    1010, 
                    27
                ], 
                [
                    1013, 
                    48
                ], 
                [
                    1016, 
                    119
                ], 
                [
                    1019, 
                    134
                ], 
                [
                    1050, 
                    104
                ], 
                [
                    1074, 
                    117
                ], 
                [
                    1108, 
                    151
                ], 
                [
                    1129, 
                    167
                ], 
                [
                    1136, 
                    162
                ], 
                [
                    1152, 
                    8
                ], 
                [
                    1340, 
                    3
                ], 
                [
                    1859, 
                    7
                ], 
                [
                    2052, 
                    -2
                ], 
                [
                    2034, 
                    647
                ], 
                [
                    1359, 
                    444
                ], 
                [
                    1366, 
                    117
                ], 
                [
                    1342, 
                    105
                ], 
                [
                    1227, 
                    71
                ], 
                [
                    1227, 
                    64
                ], 
                [
                    1220, 
                    55
                ], 
                [
                    1188, 
                    57
                ], 
                [
                    1172, 
                    69
                ], 
                [
                    1165, 
                    85
                ], 
                [
                    1161, 
                    153
                ], 
                [
                    1164, 
                    160
                ], 
                [
                    1233, 
                    176
                ], 
                [
                    1305, 
                    184
                ], 
                [
                    1295, 
                    253
                ], 
                [
                    1290, 
                    267
                ], 
                [
                    1283, 
                    278
                ], 
                [
                    1240, 
                    283
                ], 
                [
                    1230, 
                    273
                ], 
                [
                    1188, 
                    252
                ], 
                [
                    1164, 
                    199
                ], 
                [
                    1126, 
                    195
                ], 
                [
                    1116, 
                    209
                ], 
                [
                    1099, 
                    247
                ], 
                [
                    1093, 
                    270
                ], 
                [
                    1092, 
                    305
                ], 
                [
                    1096, 
                    406
                ], 
                [
                    1092, 
                    408
                ], 
                [
                    1050, 
                    403
                ], 
                [
                    1063, 
                    254
                ], 
                [
                    1061, 
                    222
                ], 
                [
                    1051, 
                    222
                ], 
                [
                    1033, 
                    230
                ], 
                [
                    1003, 
                    249
                ], 
                [
                    999, 
                    254
                ], 
                [
                    992, 
                    305
                ], 
                [
                    988, 
                    391
                ], 
                [
                    935, 
                    391
                ], 
                [
                    937, 
                    285
                ], 
                [
                    806, 
                    282
                ], 
                [
                    819, 
                    267
                ], 
                [
                    838, 
                    230
                ], 
                [
                    839, 
                    213
                ], 
                [
                    836, 
                    194
                ], 
                [
                    811, 
                    179
                ], 
                [
                    808, 
                    131
                ], 
                [
                    805, 
                    121
                ], 
                [
                    758, 
                    38
                ]
            ]
        }, 
        {
            "label": "sky", 
            "polygon": [
                [
                    1017, 
                    2
                ], 
                [
                    1019, 
                    3
                ], 
                [
                    1133, 
                    2
                ], 
                [
                    1122, 
                    126
                ], 
                [
                    1124, 
                    135
                ], 
                [
                    1087, 
                    122
                ], 
                [
                    1073, 
                    90
                ], 
                [
                    1064, 
                    80
                ], 
                [
                    1061, 
                    79
                ], 
                [
                    1054, 
                    79
                ], 
                [
                    1049, 
                    81
                ], 
                [
                    1042, 
                    83
                ], 
                [
                    1033, 
                    87
                ], 
                [
                    1026, 
                    65
                ], 
                [
                    1025, 
                    14
                ]
            ]
        }, 
        {
            "label": "traffic light", 
            "polygon": [
                [
                    1182, 
                    83
                ], 
                [
                    1181, 
                    83
                ], 
                [
                    1178, 
                    126
                ], 
                [
                    1186, 
                    128
                ], 
                [
                    1190, 
                    128
                ], 
                [
                    1191, 
                    125
                ], 
                [
                    1191, 
                    121
                ], 
                [
                    1189, 
                    85
                ], 
                [
                    1188, 
                    83
                ]
            ]
        }, 
        {
            "label": "sidewalk", 
            "polygon": [
                [
                    2043, 
                    697
                ], 
                [
                    2005, 
                    931
                ], 
                [
                    1997, 
                    917
                ], 
                [
                    1328, 
                    524
                ], 
                [
                    1320, 
                    470
                ], 
                [
                    1342, 
                    466
                ], 
                [
                    1446, 
                    501
                ], 
                [
                    1544, 
                    539
                ], 
                [
                    1790, 
                    621
                ]
            ]
        }, 
        {
            "label": "rider", 
            "polygon": [
                [
                    1247, 
                    410
                ], 
                [
                    1256, 
                    408
                ], 
                [
                    1262, 
                    414
                ], 
                [
                    1261, 
                    434
                ], 
                [
                    1263, 
                    447
                ], 
                [
                    1266, 
                    452
                ], 
                [
                    1271, 
                    455
                ], 
                [
                    1290, 
                    460
                ], 
                [
                    1250, 
                    462
                ], 
                [
                    1240, 
                    459
                ], 
                [
                    1231, 
                    459
                ], 
                [
                    1228, 
                    460
                ], 
                [
                    1223, 
                    463
                ], 
                [
                    1217, 
                    469
                ], 
                [
                    1211, 
                    478
                ], 
                [
                    1210, 
                    483
                ], 
                [
                    1204, 
                    488
                ], 
                [
                    1200, 
                    489
                ], 
                [
                    1200, 
                    487
                ], 
                [
                    1201, 
                    485
                ], 
                [
                    1213, 
                    468
                ], 
                [
                    1217, 
                    461
                ], 
                [
                    1224, 
                    444
                ], 
                [
                    1229, 
                    444
                ], 
                [
                    1238, 
                    449
                ], 
                [
                    1241, 
                    444
                ], 
                [
                    1243, 
                    437
                ], 
                [
                    1242, 
                    418
                ], 
                [
                    1244, 
                    411
                ]
            ]
        }, 
        {
            "label": "road", 
            "polygon": [
                [
                    1342, 
                    424
                ], 
                [
                    1343, 
                    427
                ], 
                [
                    1343, 
                    457
                ], 
                [
                    1303, 
                    453
                ], 
                [
                    1295, 
                    453
                ], 
                [
                    1286, 
                    451
                ], 
                [
                    1281, 
                    449
                ], 
                [
                    1278, 
                    447
                ], 
                [
                    1268, 
                    441
                ], 
                [
                    1278, 
                    432
                ], 
                [
                    1282, 
                    426
                ], 
                [
                    1285, 
                    418
                ], 
                [
                    1294, 
                    421
                ], 
                [
                    1305, 
                    423
                ], 
                [
                    1334, 
                    425
                ]
            ]
        }, 
        {
            "label": "road", 
            "polygon": [
                [
                    1212, 
                    436
                ], 
                [
                    1225, 
                    438
                ], 
                [
                    1210, 
                    444
                ], 
                [
                    1206, 
                    448
                ], 
                [
                    1191, 
                    479
                ], 
                [
                    1154, 
                    483
                ], 
                [
                    1147, 
                    483
                ], 
                [
                    1140, 
                    439
                ], 
                [
                    1138, 
                    431
                ], 
                [
                    1140, 
                    430
                ], 
                [
                    1153, 
                    434
                ], 
                [
                    1162, 
                    435
                ]
            ]
        }, 
        {
            "label": "sidewalk", 
            "polygon": [
                [
                    1109, 
                    416
                ], 
                [
                    1111, 
                    431
                ], 
                [
                    1110, 
                    434
                ], 
                [
                    1108, 
                    434
                ], 
                [
                    962, 
                    422
                ], 
                [
                    937, 
                    415
                ]
            ]
        }, 
        {
            "label": "person", 
            "polygon": [
                [
                    1141, 
                    341
                ], 
                [
                    1137, 
                    344
                ], 
                [
                    1133, 
                    347
                ], 
                [
                    1137, 
                    353
                ], 
                [
                    1137, 
                    356
                ], 
                [
                    1136, 
                    363
                ], 
                [
                    1132, 
                    374
                ], 
                [
                    1132, 
                    378
                ], 
                [
                    1132, 
                    382
                ], 
                [
                    1132, 
                    388
                ], 
                [
                    1124, 
                    406
                ], 
                [
                    1127, 
                    401
                ], 
                [
                    1132, 
                    398
                ], 
                [
                    1136, 
                    389
                ], 
                [
                    1136, 
                    388
                ], 
                [
                    1140, 
                    388
                ], 
                [
                    1143, 
                    391
                ], 
                [
                    1144, 
                    393
                ], 
                [
                    1150, 
                    409
                ], 
                [
                    1150, 
                    404
                ], 
                [
                    1148, 
                    395
                ], 
                [
                    1148, 
                    391
                ], 
                [
                    1146, 
                    384
                ], 
                [
                    1146, 
                    378
                ], 
                [
                    1149, 
                    369
                ], 
                [
                    1147, 
                    366
                ], 
                [
                    1142, 
                    361
                ], 
                [
                    1141, 
                    352
                ], 
                [
                    1142, 
                    344
                ], 
                [
                    1142, 
                    341
                ]
            ]
        }, 
        {
            "label": "building", 
            "polygon": [
                [
                    1166, 
                    293
                ], 
                [
                    1160, 
                    413
                ], 
                [
                    1230, 
                    406
                ], 
                [
                    1238, 
                    396
                ], 
                [
                    1245, 
                    392
                ], 
                [
                    1255, 
                    392
                ], 
                [
                    1270, 
                    395
                ], 
                [
                    1275, 
                    395
                ], 
                [
                    1277, 
                    394
                ], 
                [
                    1278, 
                    387
                ], 
                [
                    1286, 
                    291
                ]
            ]
        }, 
        {
            "label": "traffic light", 
            "polygon": [
                [
                    724, 
                    257
                ], 
                [
                    726, 
                    298
                ], 
                [
                    729, 
                    298
                ], 
                [
                    732, 
                    296
                ], 
                [
                    735, 
                    292
                ], 
                [
                    736, 
                    290
                ], 
                [
                    732, 
                    273
                ], 
                [
                    737, 
                    265
                ], 
                [
                    738, 
                    262
                ], 
                [
                    737, 
                    260
                ], 
                [
                    736, 
                    258
                ], 
                [
                    731, 
                    255
                ]
            ]
        }, 
        {
            "label": "vegetation", 
            "polygon": [
                [
                    733, 
                    86
                ], 
                [
                    739, 
                    168
                ], 
                [
                    737, 
                    172
                ], 
                [
                    732, 
                    192
                ], 
                [
                    731, 
                    203
                ], 
                [
                    736, 
                    214
                ], 
                [
                    758, 
                    236
                ], 
                [
                    758, 
                    239
                ], 
                [
                    762, 
                    252
                ], 
                [
                    757, 
                    266
                ], 
                [
                    763, 
                    264
                ], 
                [
                    787, 
                    264
                ], 
                [
                    791, 
                    260
                ], 
                [
                    799, 
                    240
                ], 
                [
                    797, 
                    235
                ], 
                [
                    795, 
                    230
                ], 
                [
                    789, 
                    221
                ], 
                [
                    781, 
                    211
                ], 
                [
                    762, 
                    193
                ], 
                [
                    759, 
                    181
                ], 
                [
                    759, 
                    174
                ], 
                [
                    770, 
                    149
                ], 
                [
                    772, 
                    141
                ], 
                [
                    772, 
                    130
                ], 
                [
                    768, 
                    126
                ], 
                [
                    744, 
                    118
                ], 
                [
                    737, 
                    115
                ], 
                [
                    737, 
                    105
                ], 
                [
                    737, 
                    100
                ], 
                [
                    741, 
                    90
                ], 
                [
                    740, 
                    84
                ], 
                [
                    737, 
                    83
                ]
            ]
        }, 
        {
            "label": "fence", 
            "polygon": [
                [
                    9, 
                    436
                ], 
                [
                    185, 
                    443
                ], 
                [
                    188, 
                    345
                ], 
                [
                    -2, 
                    338
                ], 
                [
                    0, 
                    339
                ]
            ]
        }, 
        {
            "label": "wall", 
            "polygon": [
                [
                    9, 
                    452
                ], 
                [
                    10, 
                    453
                ], 
                [
                    196, 
                    454
                ], 
                [
                    214, 
                    504
                ], 
                [
                    1, 
                    524
                ]
            ]
        }, 
        {
            "label": "traffic light", 
            "polygon": [
                [
                    1344, 
                    249
                ], 
                [
                    1344, 
                    283
                ], 
                [
                    1343, 
                    288
                ], 
                [
                    1342, 
                    290
                ], 
                [
                    1336, 
                    292
                ], 
                [
                    1330, 
                    291
                ], 
                [
                    1328, 
                    287
                ], 
                [
                    1327, 
                    283
                ], 
                [
                    1327, 
                    277
                ], 
                [
                    1329, 
                    270
                ], 
                [
                    1323, 
                    268
                ], 
                [
                    1322, 
                    257
                ], 
                [
                    1334, 
                    255
                ], 
                [
                    1339, 
                    253
                ], 
                [
                    1341, 
                    249
                ]
            ]
        }, 
        {
            "label": "traffic sign", 
            "polygon": [
                [
                    1329, 
                    211
                ], 
                [
                    1328, 
                    234
                ], 
                [
                    1348, 
                    237
                ], 
                [
                    1348, 
                    236
                ], 
                [
                    1350, 
                    212
                ]
            ]
        }, 
        {
            "label": "traffic sign", 
            "polygon": [
                [
                    1337, 
                    180
                ], 
                [
                    1326, 
                    188
                ], 
                [
                    1326, 
                    189
                ], 
                [
                    1326, 
                    192
                ], 
                [
                    1337, 
                    201
                ], 
                [
                    1350, 
                    192
                ]
            ]
        }, 
        {
            "label": "traffic sign", 
            "polygon": [
                [
                    1144, 
                    223
                ], 
                [
                    1140, 
                    226
                ], 
                [
                    1139, 
                    228
                ], 
                [
                    1137, 
                    236
                ], 
                [
                    1137, 
                    242
                ], 
                [
                    1139, 
                    245
                ], 
                [
                    1140, 
                    246
                ], 
                [
                    1146, 
                    249
                ], 
                [
                    1149, 
                    249
                ], 
                [
                    1152, 
                    247
                ], 
                [
                    1154, 
                    245
                ], 
                [
                    1155, 
                    238
                ], 
                [
                    1150, 
                    226
                ], 
                [
                    1148, 
                    224
                ]
            ]
        }, 
        {
            "label": "traffic sign", 
            "polygon": [
                [
                    1111, 
                    284
                ], 
                [
                    1105, 
                    288
                ], 
                [
                    1113, 
                    291
                ], 
                [
                    1127, 
                    291
                ], 
                [
                    1143, 
                    291
                ], 
                [
                    1141, 
                    286
                ], 
                [
                    1141, 
                    284
                ], 
                [
                    1119, 
                    283
                ]
            ]
        }, 
        {
            "label": "person", 
            "polygon": [
                [
                    764, 
                    325
                ], 
                [
                    761, 
                    327
                ], 
                [
                    761, 
                    328
                ], 
                [
                    759, 
                    332
                ], 
                [
                    759, 
                    335
                ], 
                [
                    758, 
                    336
                ], 
                [
                    755, 
                    340
                ], 
                [
                    750, 
                    345
                ], 
                [
                    747, 
                    349
                ], 
                [
                    747, 
                    351
                ], 
                [
                    748, 
                    352
                ], 
                [
                    765, 
                    353
                ], 
                [
                    766, 
                    353
                ], 
                [
                    770, 
                    354
                ], 
                [
                    770, 
                    358
                ], 
                [
                    772, 
                    358
                ], 
                [
                    776, 
                    357
                ], 
                [
                    782, 
                    358
                ], 
                [
                    779, 
                    353
                ], 
                [
                    777, 
                    350
                ], 
                [
                    776, 
                    349
                ], 
                [
                    773, 
                    342
                ], 
                [
                    769, 
                    337
                ], 
                [
                    769, 
                    336
                ], 
                [
                    769, 
                    330
                ], 
                [
                    768, 
                    328
                ], 
                [
                    766, 
                    326
                ], 
                [
                    764, 
                    326
                ]
            ]
        }, 
        {
            "label": "bicycle", 
            "polygon": [
                [
                    759, 
                    370
                ], 
                [
                    759, 
                    373
                ], 
                [
                    762, 
                    379
                ], 
                [
                    762, 
                    392
                ], 
                [
                    765, 
                    402
                ], 
                [
                    765, 
                    405
                ], 
                [
                    763, 
                    408
                ], 
                [
                    762, 
                    409
                ], 
                [
                    758, 
                    411
                ], 
                [
                    750, 
                    412
                ], 
                [
                    750, 
                    408
                ], 
                [
                    747, 
                    407
                ], 
                [
                    747, 
                    403
                ], 
                [
                    756, 
                    389
                ], 
                [
                    755, 
                    380
                ], 
                [
                    756, 
                    376
                ], 
                [
                    757, 
                    373
                ], 
                [
                    758, 
                    372
                ]
            ]
        }, 
        {
            "label": "pole", 
            "polygon": [
                [
                    607, 
                    443
                ], 
                [
                    611, 
                    442
                ], 
                [
                    607, 
                    263
                ], 
                [
                    604, 
                    264
                ]
            ]
        }, 
        {
            "label": "pole", 
            "polygon": [
                [
                    1293, 
                    413
                ], 
                [
                    1296, 
                    412
                ], 
                [
                    1298, 
                    405
                ], 
                [
                    1297, 
                    298
                ], 
                [
                    1293, 
                    301
                ]
            ]
        }, 
        {
            "label": "pole", 
            "polygon": [
                [
                    1336, 
                    419
                ], 
                [
                    1342, 
                    420
                ], 
                [
                    1342, 
                    413
                ], 
                [
                    1341, 
                    296
                ], 
                [
                    1336, 
                    299
                ]
            ]
        }, 
        {
            "label": "ego vehicle", 
            "polygon": [
                [
                    0, 
                    956
                ], 
                [
                    197, 
                    928
                ], 
                [
                    461, 
                    901
                ], 
                [
                    737, 
                    879
                ], 
                [
                    1002, 
                    861
                ], 
                [
                    1135, 
                    857
                ], 
                [
                    1134, 
                    854
                ], 
                [
                    1109, 
                    844
                ], 
                [
                    1096, 
                    820
                ], 
                [
                    1098, 
                    783
                ], 
                [
                    1124, 
                    759
                ], 
                [
                    1151, 
                    755
                ], 
                [
                    1179, 
                    760
                ], 
                [
                    1202, 
                    777
                ], 
                [
                    1207, 
                    806
                ], 
                [
                    1199, 
                    832
                ], 
                [
                    1189, 
                    844
                ], 
                [
                    1169, 
                    854
                ], 
                [
                    1161, 
                    856
                ], 
                [
                    1429, 
                    871
                ], 
                [
                    1724, 
                    900
                ], 
                [
                    2047, 
                    927
                ], 
                [
                    2047, 
                    1023
                ], 
                [
                    0, 
                    1023
                ]
            ]
        }, 
        {
            "label": "rectification border", 
            "polygon": [
                [
                    416, 
                    0
                ], 
                [
                    967, 
                    12
                ], 
                [
                    2047, 
                    25
                ], 
                [
                    2047, 
                    0
                ]
            ]
        }, 
        {
            "label": "rectification border", 
            "polygon": [
                [
                    2047, 
                    509
                ], 
                [
                    2047, 
                    1023
                ], 
                [
                    2037, 
                    1023
                ]
            ]
        }, 
        {
            "label": "rectification border", 
            "polygon": [
                [
                    0, 
                    0
                ], 
                [
                    0, 
                    501
                ], 
                [
                    10, 
                    434
                ], 
                [
                    19, 
                    0
                ]
            ]
        }, 
        {
            "label": "rectification border", 
            "polygon": [
                [
                    1087, 
                    981
                ], 
                [
                    0, 
                    963
                ], 
                [
                    0, 
                    1023
                ], 
                [
                    1937, 
                    1023
                ]
            ]
        }, 
        {
            "label": "out of roi", 
            "polygon": [
                [
                    0, 
                    0
                ], 
                [
                    2048, 
                    0
                ], 
                [
                    2048, 
                    1024
                ], 
                [
                    0, 
                    1024
                ], 
                [
                    0, 
                    0
                ], 
                [
                    5, 
                    5
                ], 
                [
                    5, 
                    1019
                ], 
                [
                    2043, 
                    1019
                ], 
                [
                    2043, 
                    5
                ], 
                [
                    5, 
                    5
                ]
            ]
        }
    ]
}